{"cameraMode":{"drawMode":0,"name":"Shaded","section":"Shading Mode"},"sceneLighting":true,"audioPlay":false,"sceneViewState":{"m_AlwaysRefresh":false,"showFog":true,"showSkybox":true,"showFlares":true,"showImageEffects":true,"showParticleSystems":true,"showVisualEffectGraphs":true,"m_FxEnabled":true},"in2DMode":false,"pivot":{"x":18.05763816833496,"y":-28.604211807250978,"z":32.72358322143555},"rotation":{"x":-0.5107218027114868,"y":-0.38298338651657107,"z":0.27154839038848879,"w":-0.720211386680603},"size":20.22369956970215,"orthographic":false}